binext/__init__.py
binext/binext.py
binext-0.95.dist-info/LICENSE
binext-0.95.dist-info/METADATA
binext-0.95.dist-info/WHEEL
binext-0.95.dist-info/top_level.txt
binext-0.95.dist-info/RECORD
