Metadata-Version: 2.1
Name: binext
Version: 0.95
Summary: Opinionated module for working with binary Galois extension fields
Home-page: https://github.com/jmshea/coding/tree/main/binext
Author: John M. Shea
Author-email: jshea@ece.ufl.edu
License: UNKNOWN
Keywords: finite fields binary extension galois minimal polynomials conjugates arithmetic
Platform: UNKNOWN
Classifier: Programming Language :: Python :: 3
Classifier: License :: OSI Approved :: GNU General Public License v3 (GPLv3)
Classifier: Operating System :: OS Independent
Requires-Dist: numpy
Requires-Dist: pandas
